runserver/__init__.py
runserver/runserver.py
runserver/serverrunner.py
runservermagic-3.0.1.dist-info/METADATA
runservermagic-3.0.1.dist-info/WHEEL
runservermagic-3.0.1.dist-info/top_level.txt
runservermagic-3.0.1.dist-info/RECORD
