Metadata-Version: 2.1
Name: runservermagic
Version: 3.0.1
Summary: Magic command to run Juypter's code cell on the server.
Author: Uniras
Author-email: tkappeng@gmail.com
License: MIT License
Project-URL: Homepage, https://github.com/uniras/RunServerMagic
Project-URL: Repository, https://github.com/uniras/RunServerMagic
Keywords: server,jupyter,magic
Classifier: Development Status :: 5 - Production/Stable
Classifier: Intended Audience :: Developers
Classifier: License :: OSI Approved :: MIT License
Classifier: Programming Language :: Python :: 3
Classifier: Programming Language :: Python :: 3.7
Classifier: Programming Language :: Python :: 3.8
Classifier: Programming Language :: Python :: 3.9
Classifier: Programming Language :: Python :: 3.10
Classifier: Programming Language :: Python :: 3 :: Only
Classifier: Topic :: Software Development :: Libraries
Classifier: Topic :: Software Development :: Libraries :: Python Modules
Classifier: Topic :: Utilities
